ioc_extractor/__init__.py
ioc_extractor/cli.py
ioc_extractor-0.1.0.dist-info/licenses/LICENSE
ioc_extractor-0.1.0.dist-info/METADATA
ioc_extractor-0.1.0.dist-info/WHEEL
ioc_extractor-0.1.0.dist-info/entry_points.txt
ioc_extractor-0.1.0.dist-info/top_level.txt
ioc_extractor-0.1.0.dist-info/RECORD
