Metadata-Version: 2.4
Name: ioc-extractor
Version: 0.1.0
Summary: Tool for extracting indicators of compromise from files
Author-email: Ihar Veranchuk <verenchuuk124@gmail.com>
License: MIT
Requires-Python: >=3.8
License-File: LICENSE
Requires-Dist: typer>=0.9.0
Requires-Dist: PyPDF2>=3.0.0
Requires-Dist: beautifulsoup4>=4.12.0
Requires-Dist: python-docx>=1.1.0
Requires-Dist: tldextract>=3.4.0
Dynamic: license-file
